{"content":"**Graph the equation.**\n\n$y=-1(x-3)^2+4$\n\n[[☃ grapher 1]]","images":{},"widgets":{"grapher 1":{"alignment":"default","graded":true,"options":{"availableTypes":["quadratic"],"correct":{"coords":[[3,4],[2,3]],"type":"quadratic"},"graph":{"backgroundImage":{"url":null},"editableSettings":["graph","snap","image"],"gridStep":[1,1],"labels":["x","y"],"markings":"graph","range":[[-10,10],[-10,10]],"rulerLabel":"","rulerTicks":10,"showProtractor":false,"showRuler":false,"snapStep":[1,1],"step":[1,1],"valid":true}},"static":false,"type":"grapher","version":{"major":0,"minor":0}}}}
