{"content":"**Construct a $140^\\circ$ angle.**\n\n[[☃ interactive-graph 1]]\n\n\n\n\n\n","images":{"https://ka-perseus-images.s3.amazonaws.com/d275297712ac868c7225c59423aec7bbac76a8ed.png":{"height":169,"width":397}},"widgets":{"interactive-graph 1":{"alignment":"default","graded":true,"options":{"backgroundImage":{"bottom":0,"left":0,"scale":1,"url":null},"correct":{"coords":[[7.699870174911066,-2.539041776119187],[0,-9],[-7.530523827277034,-8.999999999999998]],"match":"congruent","showAngles":false,"snapDegrees":5,"type":"angle"},"graph":{"showAngles":false,"snapDegrees":5,"type":"angle"},"labels":["x","y"],"markings":"none","range":[[-10,10],[-10,10]],"rulerLabel":"","rulerTicks":10,"showProtractor":true,"showRuler":false,"showTooltips":false,"step":[1,1]},"static":false,"type":"interactive-graph","version":{"major":0,"minor":0}}}}
