{"content":"**Make an obtuse angle by using the three black points as follows.**  \n\n**Drag the vertex of the angle to place the vertex at the correct black point.**  \n\n**Drag the points on the rays to make the rays go through the other two black points.**  \n*The arc symbol near the vertex indicates the angle being measured.*\n\n[[☃ interactive-graph 1]]\n\nThis is an obtuse angle because its measure is [[☃ dropdown 1]] $90^\\circ$.","images":{},"widgets":{"dropdown 1":{"alignment":"default","graded":true,"options":{"choices":[{"content":"éèʠúùáàĺľ ťțóò","correct":false},{"content":"ĝǧŕřéèáàťțéèŕř ťțĥȟáàńň","correct":true},{"content":"ĺľéèśŝśŝ ťțĥȟáàńň","correct":false}],"placeholder":"","static":false},"static":false,"type":"dropdown","version":{"major":0,"minor":0}},"interactive-graph 1":{"alignment":"default","graded":true,"options":{"backgroundImage":{"bottom":0,"height":400,"left":0,"scale":1,"url":"https://ka-perseus-graphie.s3.amazonaws.com/bfcb35c923169cd2ac0d7dddb11af2cbaa655367.png","width":400},"correct":{"allowReflexAngles":false,"coords":[[-1.0414686265465378,-7.322622107854323],[-4,0],[-1.0167071907949135,7.383908811954882]],"snapDegrees":2,"type":"angle"},"graph":{"allowReflexAngles":false,"snapDegrees":2,"type":"angle"},"gridStep":[1,1],"labels":["ẍẋ","ý"],"markings":"none","range":[[-10,10],[-10,10]],"rulerLabel":"","rulerTicks":10,"showProtractor":false,"showRuler":false,"showTooltips":false,"snapStep":[0.5,0.5],"step":[1,1]},"static":false,"type":"interactive-graph","version":{"major":0,"minor":0}}}}
