{"content":"**Match each expression with its appropriate interpretation.**\n\n[[☃ matcher 1]]\n\n","images":{"https://ka-perseus-images.s3.amazonaws.com/f1347fd535eef97cf4b2cc58175be73f7a61e8cc.png":{"height":528,"width":1312}},"widgets":{"dropdown 1":{"graded":true,"options":{"choices":[{"content":"<","correct":false},{"content":">","correct":true}],"placeholder":""},"type":"dropdown","version":{"major":0,"minor":0}},"expression 1":{"graded":true,"options":{"answerForms":[{"considered":"correct","form":false,"key":0,"simplify":false,"value":""}],"buttonSets":["basic"],"functions":["f","g","h"],"times":false},"type":"expression","version":{"major":1,"minor":0}},"grapher 1":{"graded":true,"options":{"availableTypes":["linear"],"correct":{"asymptote":null,"coords":null,"type":"linear"},"graph":{"backgroundImage":{"bottom":0,"left":0,"scale":1,"url":""},"box":[340,340],"labels":["x","y"],"markings":"graph","range":[[-10,10],[-10,10]],"rulerLabel":"","rulerTicks":10,"step":[1,1],"valid":true}},"type":"grapher","version":{"major":0,"minor":0}},"interactive-graph 1":{"graded":true,"options":{"backgroundImage":{"bottom":0,"left":0,"scale":1,"url":""},"correct":{"coords":null,"type":"linear"},"graph":{"type":"linear"},"labels":["x","y"],"markings":"graph","range":[[-10,10],[-10,10]],"rulerLabel":"","rulerTicks":10,"showProtractor":false,"showRuler":false,"step":[1,1]},"type":"interactive-graph","version":{"major":0,"minor":0}},"matcher 1":{"graded":true,"options":{"labels":["□□□□□□□□□□","□□□□□□□□□□□□□□"],"left":["$7 - 9$","$\\left\\lvert 7 - 9\\right\\rvert$","$7 + (-7)$"],"orderMatters":false,"padding":true,"right":["The number $9$ to the left of $7$ on the horizontal number line","The distance between $7$ and $9$ on the number line","□□□□ □□ □□□□"]},"type":"matcher","version":{"major":0,"minor":0}},"number-line 1":{"graded":true,"options":{"correctRel":"eq","correctX":null,"divisionRange":[1,12],"initialX":null,"labelRange":[null,null],"labelStyle":"decimal","labelTicks":true,"numDivisions":5,"range":[0,10],"snapDivisions":2,"tickStep":null},"type":"number-line","version":{"major":0,"minor":0}},"radio 1":{"graded":true,"options":{"choices":[{"content":"$|a - b| \\cdot |c - d|$","correct":false}],"deselectEnabled":false,"displayCount":null,"multipleSelect":false,"noneOfTheAbove":false,"onePerLine":true,"randomize":false},"type":"radio","version":{"major":0,"minor":0}},"sorter 1":{"graded":true,"options":{"correct":["$|a - e|$","$|b - f|$","$|a - c|$"],"layout":"horizontal","padding":true},"type":"sorter","version":{"major":0,"minor":0}}}}
