[{"author_key":"None","author_names":["Jeff Dodds"],"content_id":"x97f3f387580069b6","content_kind":"AssessmentItem","content_kind_code":"i","created_by":"Key('UserData', 'user_id_key_http://nouserid.khanacademy.org/9af3e69189683d7009d70f10da14a472')","creation_date":"2021-03-31 21:10:05.826940","do_not_publish":false,"hide":false,"id":"x97f3f387580069b6","imported_from_sha":"","item_data":{"answerArea":{"calculator":true,"chi2Table":false,"periodicTable":false,"tTable":false,"zTable":false},"hints":[{"content":"crwdns6970564:0$w$crwdnd6970564:0$wcrwdnd6970564:0{a}crwdnd6970564:0{b}crwdnd6970564:0$wcrwdnd6970564:0{r}crwdnd6970564:0$z$crwdne6970564:0","images":{},"replace":false,"widgets":{"image 2":{"alignment":"block","graded":true,"options":{"alt":"","backgroundImage":{"height":325,"url":"crwdns6969930:0crwdne6969930:0","width":325},"box":[325,325],"caption":"","labels":[],"range":[[0,10],[0,10]],"static":false,"title":""},"static":false,"type":"image","version":{"major":0,"minor":0}}}},{"content":"crwdns6970022:0{align}crwdnd6970022:0{align}crwdne6970022:0","images":{},"replace":false,"widgets":{}},{"content":"crwdns6970202:0{3}crwdnd6970202:0{4}crwdnd6970202:0{5}crwdne6970202:0","images":{},"replace":false,"widgets":{"image 1":{"alignment":"block","graded":true,"options":{"alt":"","backgroundImage":{"height":325,"url":"crwdns6970130:0crwdne6970130:0","width":325},"box":[325,325],"caption":"","labels":[],"range":[[0,10],[0,10]],"static":false,"title":""},"static":false,"type":"image","version":{"major":0,"minor":0}}}},{"content":"crwdns6970012:0$zcrwdne6970012:0","images":{},"replace":false,"widgets":{"image 1":{"alignment":"block","graded":true,"options":{"alt":"","backgroundImage":{"height":325,"url":"crwdns6970286:0crwdne6970286:0","width":325},"box":[325,325],"caption":"","labels":[],"range":[[0,10],[0,10]],"static":false,"title":""},"static":false,"type":"image","version":{"major":0,"minor":0}}}}],"itemDataVersion":{"major":0,"minor":1},"question":{"content":"crwdns6970412:0$zcrwdnd6970412:0$z$crwdne6970412:0","images":{},"widgets":{"interactive-graph 1":{"alignment":"default","graded":true,"options":{"backgroundImage":{"height":400,"url":"web+graphie://ka-perseus-graphie.s3.amazonaws.com/733ef19bc76a8a21bcf789ed01943d508ba4056a","width":400},"correct":{"coords":[[3,-4]],"type":"point"},"graph":{"type":"point"},"gridStep":[1,1],"labels":["crwdns2648390:0crwdne2648390:0","crwdns3083011:0crwdne3083011:0"],"markings":"none","range":[[-6,6],[-6,6]],"rulerLabel":"","rulerTicks":10,"showProtractor":false,"showRuler":false,"showTooltips":false,"snapStep":[1,1],"step":[1,1]},"static":false,"type":"interactive-graph","version":{"major":0,"minor":0}}}}},"item_shape_type":"item","key":"8ee0307627b8791b7893ff4000797768da4a6215","name":"1.1 3-4i TG","perseus_api_major_version":0,"requires_screen_or_mouse":true,"sha":"8ee0307627b8791b7893ff4000797768da4a6215","tags":[]},{"author_key":"None","author_names":["Jeff Dodds"],"content_id":"x16551954c48519ca","content_kind":"AssessmentItem","content_kind_code":"i","created_by":"Key('UserData', 'user_id_key_http://nouserid.khanacademy.org/9af3e69189683d7009d70f10da14a472')","creation_date":"2021-03-31 21:10:00.724371","do_not_publish":false,"hide":false,"id":"x16551954c48519ca","imported_from_sha":"","item_data":{"answerArea":{"calculator":true,"chi2Table":false,"periodicTable":false,"tTable":false,"zTable":false},"hints":[{"content":"crwdns6970564:0$w$crwdnd6970564:0$wcrwdnd6970564:0{a}crwdnd6970564:0{b}crwdnd6970564:0$wcrwdnd6970564:0{r}crwdnd6970564:0$z$crwdne6970564:0","images":{},"replace":false,"widgets":{"image 2":{"alignment":"block","graded":true,"options":{"alt":"","backgroundImage":{"height":325,"url":"crwdns6969930:0crwdne6969930:0","width":325},"box":[325,325],"caption":"","labels":[],"range":[[0,10],[0,10]],"static":false,"title":""},"static":false,"type":"image","version":{"major":0,"minor":0}}}},{"content":"crwdns6970158:0{align}crwdnd6970158:0{29}crwdnd6970158:0{29}crwdnd6970158:0{align}crwdne6970158:0","images":{},"replace":false,"widgets":{}},{"content":"crwdns6970294:0{2}crwdnd6970294:0{5}crwdnd6970294:0{29}crwdne6970294:0","images":{},"replace":false,"widgets":{"image 1":{"alignment":"block","graded":true,"options":{"alt":"","backgroundImage":{"height":325,"url":"crwdns6970278:0crwdne6970278:0","width":325},"box":[325,325],"caption":"","labels":[],"range":[[0,10],[0,10]],"static":false,"title":""},"static":false,"type":"image","version":{"major":0,"minor":0}}}},{"content":"crwdns6970454:0$zcrwdnd6970454:0{29}crwdne6970454:0","images":{},"replace":false,"widgets":{"image 1":{"alignment":"block","graded":true,"options":{"alt":"","backgroundImage":{"height":325,"url":"crwdns6970072:0crwdne6970072:0","width":325},"box":[325,325],"caption":"","labels":[],"range":[[0,10],[0,10]],"static":false,"title":""},"static":false,"type":"image","version":{"major":0,"minor":0}}}}],"itemDataVersion":{"major":0,"minor":1},"question":{"content":"crwdns6970430:0$zcrwdnd6970430:0{29}crwdnd6970430:0$z$crwdne6970430:0","images":{},"widgets":{"interactive-graph 1":{"alignment":"default","graded":true,"options":{"backgroundImage":{"height":400,"url":"web+graphie://ka-perseus-graphie.s3.amazonaws.com/733ef19bc76a8a21bcf789ed01943d508ba4056a","width":400},"correct":{"coords":[[-2,-5]],"type":"point"},"graph":{"type":"point"},"gridStep":[1,1],"labels":["crwdns2648390:0crwdne2648390:0","crwdns3083011:0crwdne3083011:0"],"markings":"none","range":[[-6,6],[-6,6]],"rulerLabel":"","rulerTicks":10,"showProtractor":false,"showRuler":false,"showTooltips":false,"snapStep":[1,1],"step":[1,1]},"static":false,"type":"interactive-graph","version":{"major":0,"minor":0}}}}},"item_shape_type":"item","key":"478584890145a5a9729b2d946041a8a7d0e78905","name":"1.2 -2-5i","perseus_api_major_version":0,"requires_screen_or_mouse":true,"sha":"478584890145a5a9729b2d946041a8a7d0e78905","tags":[]},{"author_key":"None","author_names":["Jeff Dodds"],"content_id":"x62baec7968a254d9","content_kind":"AssessmentItem","content_kind_code":"i","created_by":"Key('UserData', 'user_id_key_http://nouserid.khanacademy.org/9af3e69189683d7009d70f10da14a472')","creation_date":"2021-03-31 21:09:56.093960","do_not_publish":false,"hide":false,"id":"x62baec7968a254d9","imported_from_sha":"","item_data":{"answerArea":{"calculator":true,"chi2Table":false,"periodicTable":false,"tTable":false,"zTable":false},"hints":[{"content":"crwdns6970564:0$w$crwdnd6970564:0$wcrwdnd6970564:0{a}crwdnd6970564:0{b}crwdnd6970564:0$wcrwdnd6970564:0{r}crwdnd6970564:0$z$crwdne6970564:0","images":{},"replace":false,"widgets":{"image 2":{"alignment":"block","graded":true,"options":{"alt":"","backgroundImage":{"height":325,"url":"crwdns6969930:0crwdne6969930:0","width":325},"box":[325,325],"caption":"","labels":[],"range":[[0,10],[0,10]],"static":false,"title":""},"static":false,"type":"image","version":{"major":0,"minor":0}}}},{"content":"crwdns6970326:0{align}crwdnd6970326:0{34}crwdnd6970326:0{34}crwdnd6970326:0{align}crwdne6970326:0","images":{},"replace":false,"widgets":{}},{"content":"crwdns6970450:0{5}crwdnd6970450:0{3}crwdnd6970450:0{34}crwdne6970450:0","images":{},"replace":false,"widgets":{"image 1":{"alignment":"block","graded":true,"options":{"alt":"","backgroundImage":{"height":325,"url":"crwdns6970376:0crwdne6970376:0","width":325},"box":[325,325],"caption":"","labels":[],"range":[[0,10],[0,10]],"static":false,"title":""},"static":false,"type":"image","version":{"major":0,"minor":0}}}},{"content":"crwdns6970268:0$zcrwdnd6970268:0{34}crwdne6970268:0","images":{},"replace":false,"widgets":{"image 1":{"alignment":"block","graded":true,"options":{"alt":"","backgroundImage":{"height":325,"url":"crwdns6970264:0crwdne6970264:0","width":325},"box":[325,325],"caption":"","labels":[],"range":[[0,10],[0,10]],"static":false,"title":""},"static":false,"type":"image","version":{"major":0,"minor":0}}}}],"itemDataVersion":{"major":0,"minor":1},"question":{"content":"crwdns6970256:0$zcrwdnd6970256:0{34}crwdnd6970256:0$z$crwdne6970256:0","images":{},"widgets":{"interactive-graph 1":{"alignment":"default","graded":true,"options":{"backgroundImage":{"height":400,"url":"web+graphie://ka-perseus-graphie.s3.amazonaws.com/733ef19bc76a8a21bcf789ed01943d508ba4056a","width":400},"correct":{"coords":[[5,-3]],"type":"point"},"graph":{"type":"point"},"gridStep":[1,1],"labels":["crwdns2648390:0crwdne2648390:0","crwdns3083011:0crwdne3083011:0"],"markings":"none","range":[[-6,6],[-6,6]],"rulerLabel":"","rulerTicks":10,"showProtractor":false,"showRuler":false,"showTooltips":false,"snapStep":[1,1],"step":[1,1]},"static":false,"type":"interactive-graph","version":{"major":0,"minor":0}}}}},"item_shape_type":"item","key":"54eadd0fc4705fd2a006c2dc053bdffbe2658e55","name":"1.3 5-3i","perseus_api_major_version":0,"requires_screen_or_mouse":true,"sha":"54eadd0fc4705fd2a006c2dc053bdffbe2658e55","tags":[]},{"author_key":"None","author_names":["Jeff Dodds"],"content_id":"xd2477dd23ebf424a","content_kind":"AssessmentItem","content_kind_code":"i","created_by":"Key('UserData', 'user_id_key_http://nouserid.khanacademy.org/9af3e69189683d7009d70f10da14a472')","creation_date":"2021-03-31 21:09:51.687350","do_not_publish":false,"hide":false,"id":"xd2477dd23ebf424a","imported_from_sha":"","item_data":{"answerArea":{"calculator":true,"chi2Table":false,"periodicTable":false,"tTable":false,"zTable":false},"hints":[{"content":"crwdns6970564:0$w$crwdnd6970564:0$wcrwdnd6970564:0{a}crwdnd6970564:0{b}crwdnd6970564:0$wcrwdnd6970564:0{r}crwdnd6970564:0$z$crwdne6970564:0","images":{},"replace":false,"widgets":{"image 2":{"alignment":"block","graded":true,"options":{"alt":"","backgroundImage":{"height":325,"url":"crwdns6969930:0crwdne6969930:0","width":325},"box":[325,325],"caption":"","labels":[],"range":[[0,10],[0,10]],"static":false,"title":""},"static":false,"type":"image","version":{"major":0,"minor":0}}}},{"content":"crwdns6970538:0{align}crwdnd6970538:0{17}crwdnd6970538:0{17}crwdnd6970538:0{align}crwdne6970538:0","images":{},"replace":false,"widgets":{}},{"content":"crwdns6970048:0{1}crwdnd6970048:0{4}crwdnd6970048:0{17}crwdne6970048:0","images":{},"replace":false,"widgets":{"image 1":{"alignment":"block","graded":true,"options":{"alt":"","backgroundImage":{"height":325,"url":"crwdns6970214:0crwdne6970214:0","width":325},"box":[325,325],"caption":"","labels":[],"range":[[0,10],[0,10]],"static":false,"title":""},"static":false,"type":"image","version":{"major":0,"minor":0}}}},{"content":"crwdns6970020:0$zcrwdnd6970020:0{17}crwdne6970020:0","images":{},"replace":false,"widgets":{"image 1":{"alignment":"block","graded":true,"options":{"alt":"","backgroundImage":{"height":325,"url":"crwdns6970160:0crwdne6970160:0","width":325},"box":[325,325],"caption":"","labels":[],"range":[[0,10],[0,10]],"static":false,"title":""},"static":false,"type":"image","version":{"major":0,"minor":0}}}}],"itemDataVersion":{"major":0,"minor":1},"question":{"content":"crwdns6970276:0$zcrwdnd6970276:0{17}crwdnd6970276:0$z$crwdne6970276:0","images":{},"widgets":{"interactive-graph 1":{"alignment":"default","graded":true,"options":{"backgroundImage":{"height":400,"url":"web+graphie://ka-perseus-graphie.s3.amazonaws.com/733ef19bc76a8a21bcf789ed01943d508ba4056a","width":400},"correct":{"coords":[[-1,4]],"type":"point"},"graph":{"type":"point"},"gridStep":[1,1],"labels":["crwdns2648390:0crwdne2648390:0","crwdns3083011:0crwdne3083011:0"],"markings":"none","range":[[-6,6],[-6,6]],"rulerLabel":"","rulerTicks":10,"showProtractor":false,"showRuler":false,"showTooltips":false,"snapStep":[1,1],"step":[1,1]},"static":false,"type":"interactive-graph","version":{"major":0,"minor":0}}}}},"item_shape_type":"item","key":"5b74efe9a7bce59289eda4b70636e8135e927366","name":"1.4 -1+4i","perseus_api_major_version":0,"requires_screen_or_mouse":true,"sha":"5b74efe9a7bce59289eda4b70636e8135e927366","tags":[]},{"author_key":"None","author_names":["Jeff Dodds"],"content_id":"xc5eba3592dd6a07a","content_kind":"AssessmentItem","content_kind_code":"i","created_by":"Key('UserData', 'user_id_key_http://nouserid.khanacademy.org/9af3e69189683d7009d70f10da14a472')","creation_date":"2021-03-31 21:09:47.420390","do_not_publish":false,"hide":false,"id":"xc5eba3592dd6a07a","imported_from_sha":"","item_data":{"answerArea":{"calculator":true,"chi2Table":false,"periodicTable":false,"tTable":false,"zTable":false},"hints":[{"content":"crwdns6970564:0$w$crwdnd6970564:0$wcrwdnd6970564:0{a}crwdnd6970564:0{b}crwdnd6970564:0$wcrwdnd6970564:0{r}crwdnd6970564:0$z$crwdne6970564:0","images":{},"replace":false,"widgets":{"image 2":{"alignment":"block","graded":true,"options":{"alt":"","backgroundImage":{"height":325,"url":"crwdns6969930:0crwdne6969930:0","width":325},"box":[325,325],"caption":"","labels":[],"range":[[0,10],[0,10]],"static":false,"title":""},"static":false,"type":"image","version":{"major":0,"minor":0}}}},{"content":"crwdns6970446:0{align}crwdnd6970446:0{10}crwdnd6970446:0{10}crwdnd6970446:0{align}crwdne6970446:0","images":{},"replace":false,"widgets":{}},{"content":"crwdns6970150:0{3}crwdnd6970150:0{1}crwdnd6970150:0{10}crwdne6970150:0","images":{},"replace":false,"widgets":{"image 1":{"alignment":"block","graded":true,"options":{"alt":"","backgroundImage":{"height":325,"url":"crwdns6970416:0crwdne6970416:0","width":325},"box":[325,325],"caption":"","labels":[],"range":[[0,10],[0,10]],"static":false,"title":""},"static":false,"type":"image","version":{"major":0,"minor":0}}}},{"content":"crwdns6970054:0$zcrwdnd6970054:0{10}crwdne6970054:0","images":{},"replace":false,"widgets":{"image 1":{"alignment":"block","graded":true,"options":{"alt":"","backgroundImage":{"height":325,"url":"crwdns6970386:0crwdne6970386:0","width":325},"box":[325,325],"caption":"","labels":[],"range":[[0,10],[0,10]],"static":false,"title":""},"static":false,"type":"image","version":{"major":0,"minor":0}}}}],"itemDataVersion":{"major":0,"minor":1},"question":{"content":"crwdns6970304:0$zcrwdnd6970304:0{10}crwdnd6970304:0$z$crwdne6970304:0","images":{},"widgets":{"interactive-graph 1":{"alignment":"default","graded":true,"options":{"backgroundImage":{"height":400,"url":"web+graphie://ka-perseus-graphie.s3.amazonaws.com/733ef19bc76a8a21bcf789ed01943d508ba4056a","width":400},"correct":{"coords":[[-3,1]],"type":"point"},"graph":{"type":"point"},"gridStep":[1,1],"labels":["crwdns2648390:0crwdne2648390:0","crwdns3083011:0crwdne3083011:0"],"markings":"none","range":[[-6,6],[-6,6]],"rulerLabel":"","rulerTicks":10,"showProtractor":false,"showRuler":false,"showTooltips":false,"snapStep":[1,1],"step":[1,1]},"static":false,"type":"interactive-graph","version":{"major":0,"minor":0}}}}},"item_shape_type":"item","key":"5b4181ae3e9aed580de9e01403d111d13b5adb10","name":"1.5 -3+i","perseus_api_major_version":0,"requires_screen_or_mouse":true,"sha":"5b4181ae3e9aed580de9e01403d111d13b5adb10","tags":[]},{"author_key":"None","author_names":["Jeff Dodds"],"content_id":"x3198f1e6e73a7322","content_kind":"AssessmentItem","content_kind_code":"i","created_by":"Key('UserData', 'user_id_key_http://nouserid.khanacademy.org/9af3e69189683d7009d70f10da14a472')","creation_date":"2021-03-31 21:09:42.876782","do_not_publish":false,"hide":false,"id":"x3198f1e6e73a7322","imported_from_sha":"","item_data":{"answerArea":{"calculator":true,"chi2Table":false,"periodicTable":false,"tTable":false,"zTable":false},"hints":[{"content":"crwdns6970564:0$w$crwdnd6970564:0$wcrwdnd6970564:0{a}crwdnd6970564:0{b}crwdnd6970564:0$wcrwdnd6970564:0{r}crwdnd6970564:0$z$crwdne6970564:0","images":{},"replace":false,"widgets":{"image 2":{"alignment":"block","graded":true,"options":{"alt":"","backgroundImage":{"height":325,"url":"crwdns6969930:0crwdne6969930:0","width":325},"box":[325,325],"caption":"","labels":[],"range":[[0,10],[0,10]],"static":false,"title":""},"static":false,"type":"image","version":{"major":0,"minor":0}}}},{"content":"crwdns6970238:0{align}crwdnd6970238:0{5}crwdnd6970238:0{5}crwdnd6970238:0{align}crwdne6970238:0","images":{},"replace":false,"widgets":{}},{"content":"crwdns6970434:0{4}crwdnd6970434:0{2}crwdnd6970434:0{5}crwdne6970434:0","images":{},"replace":false,"widgets":{"image 1":{"alignment":"block","graded":true,"options":{"alt":"","backgroundImage":{"height":325,"url":"crwdns6970448:0crwdne6970448:0","width":325},"box":[325,325],"caption":"","labels":[],"range":[[0,10],[0,10]],"static":false,"title":""},"static":false,"type":"image","version":{"major":0,"minor":0}}}},{"content":"crwdns6969974:0$zcrwdnd6969974:0{5}crwdne6969974:0","images":{},"replace":false,"widgets":{"image 1":{"alignment":"block","graded":true,"options":{"alt":"","backgroundImage":{"height":325,"url":"crwdns6970390:0crwdne6970390:0","width":325},"box":[325,325],"caption":"","labels":[],"range":[[0,10],[0,10]],"static":false,"title":""},"static":false,"type":"image","version":{"major":0,"minor":0}}}}],"itemDataVersion":{"major":0,"minor":1},"question":{"content":"crwdns6970120:0$zcrwdnd6970120:0{5}crwdnd6970120:0$z$crwdne6970120:0","images":{},"widgets":{"interactive-graph 1":{"alignment":"default","graded":true,"options":{"backgroundImage":{"height":400,"url":"web+graphie://ka-perseus-graphie.s3.amazonaws.com/733ef19bc76a8a21bcf789ed01943d508ba4056a","width":400},"correct":{"coords":[[4,2]],"type":"point"},"graph":{"type":"point"},"gridStep":[1,1],"labels":["crwdns2648390:0crwdne2648390:0","crwdns3083011:0crwdne3083011:0"],"markings":"none","range":[[-6,6],[-6,6]],"rulerLabel":"","rulerTicks":10,"showProtractor":false,"showRuler":false,"showTooltips":false,"snapStep":[1,1],"step":[1,1]},"static":false,"type":"interactive-graph","version":{"major":0,"minor":0}}}}},"item_shape_type":"item","key":"6858896eea3f822a1e19f305b25642aa10130c5f","name":"1.6 4+2i","perseus_api_major_version":0,"requires_screen_or_mouse":true,"sha":"6858896eea3f822a1e19f305b25642aa10130c5f","tags":[]},{"author_key":"None","author_names":["Jeff Dodds"],"content_id":"x5ff94bb6dd598adf","content_kind":"AssessmentItem","content_kind_code":"i","created_by":"Key('UserData', 'user_id_key_http://nouserid.khanacademy.org/9af3e69189683d7009d70f10da14a472')","creation_date":"2021-03-31 21:09:38.350933","do_not_publish":false,"hide":false,"id":"x5ff94bb6dd598adf","imported_from_sha":"","item_data":{"answerArea":{"calculator":true,"chi2Table":false,"periodicTable":false,"tTable":false,"zTable":false},"hints":[{"content":"crwdns6970108:0$w$crwdnd6970108:0$wcrwdnd6970108:0{a}crwdnd6970108:0{b}crwdnd6970108:0$wcrwdnd6970108:0{r}crwdnd6970108:0$z$crwdnd6970108:0$z$crwdne6970108:0","images":{},"replace":false,"widgets":{"image 1":{"alignment":"block","graded":true,"options":{"alt":"","backgroundImage":{"height":325,"url":"crwdns6969930:0crwdne6969930:0","width":325},"box":[325,325],"caption":"","labels":[],"range":[[0,10],[0,10]],"static":false,"title":""},"static":false,"type":"image","version":{"major":0,"minor":0}}}},{"content":"crwdns6970284:0{align}crwdnd6970284:0{1}crwdnd6970284:0{2}crwdnd6970284:0{2}crwdnd6970284:0{align}crwdne6970284:0","images":{},"replace":false,"widgets":{}},{"content":"crwdns6970262:0$-2+3.5i$crwdnd6970262:0$z$crwdne6970262:0","images":{},"replace":false,"widgets":{}}],"itemDataVersion":{"major":0,"minor":1},"question":{"content":"crwdns6970360:0$zcrwdnd6970360:0$z$crwdne6970360:0","images":{},"widgets":{"radio 1":{"alignment":"default","graded":true,"options":{"choices":[{"content":"crwdns6970368:0$-3.5+2i$crwdne6970368:0","correct":false},{"content":"crwdns6970366:0$-2+3.5i$crwdne6970366:0","correct":true},{"content":"crwdns6970152:0$2-3.5i$crwdne6970152:0","correct":false,"isNoneOfTheAbove":false},{"content":"crwdns6970302:0$3.5-2i$crwdne6970302:0","correct":false,"isNoneOfTheAbove":false}],"countChoices":false,"deselectEnabled":false,"displayCount":null,"hasNoneOfTheAbove":false,"multipleSelect":false,"randomize":true},"static":false,"type":"radio","version":{"major":1,"minor":0}}}}},"item_shape_type":"item","key":"7c3554234bb4deca2e5492214c68828137aa46e8","name":"2.1 4, 120º","perseus_api_major_version":3,"requires_screen_or_mouse":true,"sha":"7c3554234bb4deca2e5492214c68828137aa46e8","tags":[]},{"author_key":"None","author_names":["Jeff Dodds"],"content_id":"xe175ebd0c055bbf5","content_kind":"AssessmentItem","content_kind_code":"i","created_by":"Key('UserData', 'user_id_key_http://nouserid.khanacademy.org/9af3e69189683d7009d70f10da14a472')","creation_date":"2021-03-31 21:09:33.462230","do_not_publish":false,"hide":false,"id":"xe175ebd0c055bbf5","imported_from_sha":"","item_data":{"answerArea":{"calculator":true,"chi2Table":false,"periodicTable":false,"tTable":false,"zTable":false},"hints":[{"content":"crwdns6970108:0$w$crwdnd6970108:0$wcrwdnd6970108:0{a}crwdnd6970108:0{b}crwdnd6970108:0$wcrwdnd6970108:0{r}crwdnd6970108:0$z$crwdnd6970108:0$z$crwdne6970108:0","images":{},"replace":false,"widgets":{"image 1":{"alignment":"block","graded":true,"options":{"alt":"","backgroundImage":{"height":325,"url":"crwdns6969930:0crwdne6969930:0","width":325},"box":[325,325],"caption":"","labels":[],"range":[[0,10],[0,10]],"static":false,"title":""},"static":false,"type":"image","version":{"major":0,"minor":0}}}},{"content":"crwdns6969918:0{align}crwdnd6969918:0{align}crwdne6969918:0","images":{},"replace":false,"widgets":{}},{"content":"crwdns6970518:0$z$crwdne6970518:0","images":{},"replace":false,"widgets":{}}],"itemDataVersion":{"major":0,"minor":1},"question":{"content":"crwdns6970490:0$zcrwdnd6970490:0$z$crwdne6970490:0","images":{},"widgets":{"radio 1":{"alignment":"default","graded":true,"options":{"choices":[{"content":"crwdns6970230:0crwdne6970230:0","correct":true},{"content":"crwdns6970566:0crwdne6970566:0","correct":false},{"content":"crwdns6970470:0crwdne6970470:0","correct":false,"isNoneOfTheAbove":false},{"content":"crwdns6970174:0crwdne6970174:0","correct":false,"isNoneOfTheAbove":false}],"countChoices":false,"deselectEnabled":false,"displayCount":null,"hasNoneOfTheAbove":false,"multipleSelect":false,"randomize":true},"static":false,"type":"radio","version":{"major":1,"minor":0}}}}},"item_shape_type":"item","key":"a90a230719ea4318c7929312905032574c85517b","name":"2.2 8, 240º","perseus_api_major_version":3,"requires_screen_or_mouse":true,"sha":"a90a230719ea4318c7929312905032574c85517b","tags":[]},{"author_key":"None","author_names":["Jeff Dodds"],"content_id":"xf3d2117f73f0e8d7","content_kind":"AssessmentItem","content_kind_code":"i","created_by":"Key('UserData', 'user_id_key_http://nouserid.khanacademy.org/9af3e69189683d7009d70f10da14a472')","creation_date":"2021-03-31 21:38:19.102521","do_not_publish":false,"hide":false,"id":"xf3d2117f73f0e8d7","imported_from_sha":"","item_data":{"answerArea":{"calculator":true,"chi2Table":false,"periodicTable":false,"tTable":false,"zTable":false},"hints":[{"content":"crwdns6970108:0$w$crwdnd6970108:0$wcrwdnd6970108:0{a}crwdnd6970108:0{b}crwdnd6970108:0$wcrwdnd6970108:0{r}crwdnd6970108:0$z$crwdnd6970108:0$z$crwdne6970108:0","images":{},"replace":false,"widgets":{"image 1":{"alignment":"block","graded":true,"options":{"alt":"","backgroundImage":{"height":325,"url":"crwdns6969930:0crwdne6969930:0","width":325},"box":[325,325],"caption":"","labels":[],"range":[[0,10],[0,10]],"static":false,"title":""},"static":false,"type":"image","version":{"major":0,"minor":0}}}},{"content":"crwdns6970528:0{align}crwdnd6970528:0{align}crwdne6970528:0","images":{},"replace":false,"widgets":{}},{"content":"crwdns6970508:0$z$crwdne6970508:0","images":{},"replace":false,"widgets":{}}],"itemDataVersion":{"major":0,"minor":1},"question":{"content":"crwdns6970424:0$zcrwdnd6970424:0$z$crwdne6970424:0","images":{},"widgets":{"radio 1":{"alignment":"default","graded":true,"options":{"choices":[{"content":"crwdns6970240:0crwdne6970240:0","correct":true},{"content":"crwdns6969978:0crwdne6969978:0","correct":false},{"content":"crwdns6970520:0crwdne6970520:0","correct":false,"isNoneOfTheAbove":false},{"content":"crwdns6970484:0crwdne6970484:0","correct":false,"isNoneOfTheAbove":false}],"countChoices":false,"deselectEnabled":false,"displayCount":null,"hasNoneOfTheAbove":false,"multipleSelect":false,"randomize":true},"static":false,"type":"radio","version":{"major":1,"minor":0}}}}},"item_shape_type":"item","key":"5fee154bd9892dabd83450ac4b8255117a302f56","name":"2.3 3, 355º","perseus_api_major_version":3,"requires_screen_or_mouse":true,"sha":"5fee154bd9892dabd83450ac4b8255117a302f56","tags":[]},{"author_key":"None","author_names":["Jeff Dodds"],"content_id":"x46dd3a48c6ba1048","content_kind":"AssessmentItem","content_kind_code":"i","created_by":"Key('UserData', 'user_id_key_http://nouserid.khanacademy.org/9af3e69189683d7009d70f10da14a472')","creation_date":"2021-03-31 21:40:37.950792","do_not_publish":false,"hide":false,"id":"x46dd3a48c6ba1048","imported_from_sha":"","item_data":{"answerArea":{"calculator":true,"chi2Table":false,"periodicTable":false,"tTable":false,"zTable":false},"hints":[{"content":"crwdns6970108:0$w$crwdnd6970108:0$wcrwdnd6970108:0{a}crwdnd6970108:0{b}crwdnd6970108:0$wcrwdnd6970108:0{r}crwdnd6970108:0$z$crwdnd6970108:0$z$crwdne6970108:0","images":{},"replace":false,"widgets":{"image 1":{"alignment":"block","graded":true,"options":{"alt":"","backgroundImage":{"height":325,"url":"crwdns6969930:0crwdne6969930:0","width":325},"box":[325,325],"caption":"","labels":[],"range":[[0,10],[0,10]],"static":false,"title":""},"static":false,"type":"image","version":{"major":0,"minor":0}}}},{"content":"crwdns6970136:0{align}crwdnd6970136:0{align}crwdne6970136:0","images":{},"replace":false,"widgets":{}},{"content":"crwdns6970394:0$z$crwdne6970394:0","images":{},"replace":false,"widgets":{}}],"itemDataVersion":{"major":0,"minor":1},"question":{"content":"crwdns6970116:0$zcrwdnd6970116:0$z$crwdne6970116:0","images":{},"widgets":{"radio 1":{"alignment":"default","graded":true,"options":{"choices":[{"content":"crwdns6969916:0crwdne6969916:0","correct":true},{"content":"crwdns6970138:0crwdne6970138:0","correct":false},{"content":"crwdns6970074:0crwdne6970074:0","correct":false,"isNoneOfTheAbove":false},{"content":"crwdns6970002:0crwdne6970002:0","correct":false,"isNoneOfTheAbove":false}],"countChoices":false,"deselectEnabled":false,"displayCount":null,"hasNoneOfTheAbove":false,"multipleSelect":false,"randomize":true},"static":false,"type":"radio","version":{"major":1,"minor":0}}}}},"item_shape_type":"item","key":"1638d845bed6addd303d4ab04f8dd7c7726fb6d5","name":"2.4 2, 70º","perseus_api_major_version":3,"requires_screen_or_mouse":true,"sha":"1638d845bed6addd303d4ab04f8dd7c7726fb6d5","tags":[]},{"author_key":"None","author_names":["Jeff Dodds"],"content_id":"x58e340bbb9a8c1ac","content_kind":"AssessmentItem","content_kind_code":"i","created_by":"Key('UserData', 'user_id_key_http://nouserid.khanacademy.org/9af3e69189683d7009d70f10da14a472')","creation_date":"2021-03-31 21:09:19.762600","do_not_publish":false,"hide":false,"id":"x58e340bbb9a8c1ac","imported_from_sha":"","item_data":{"answerArea":{"calculator":true,"chi2Table":false,"periodicTable":false,"tTable":false,"zTable":false},"hints":[{"content":"crwdns6970108:0$w$crwdnd6970108:0$wcrwdnd6970108:0{a}crwdnd6970108:0{b}crwdnd6970108:0$wcrwdnd6970108:0{r}crwdnd6970108:0$z$crwdnd6970108:0$z$crwdne6970108:0","images":{},"replace":false,"widgets":{"image 1":{"alignment":"block","graded":true,"options":{"alt":"","backgroundImage":{"height":325,"url":"crwdns6969930:0crwdne6969930:0","width":325},"box":[325,325],"caption":"","labels":[],"range":[[0,10],[0,10]],"static":false,"title":""},"static":false,"type":"image","version":{"major":0,"minor":0}}}},{"content":"crwdns6970094:0{align}crwdnd6970094:0{align}crwdne6970094:0","images":{},"replace":false,"widgets":{}},{"content":"crwdns6970298:0$z$crwdne6970298:0","images":{},"replace":false,"widgets":{}}],"itemDataVersion":{"major":0,"minor":1},"question":{"content":"crwdns6970410:0$zcrwdnd6970410:0$z$crwdne6970410:0","images":{},"widgets":{"radio 1":{"alignment":"default","graded":true,"options":{"choices":[{"content":"crwdns6970502:0crwdne6970502:0","correct":true},{"content":"crwdns6970232:0crwdne6970232:0","correct":false},{"content":"crwdns6970270:0crwdne6970270:0","correct":false,"isNoneOfTheAbove":false},{"content":"crwdns6970186:0crwdne6970186:0","correct":false,"isNoneOfTheAbove":false}],"countChoices":false,"deselectEnabled":false,"displayCount":null,"hasNoneOfTheAbove":false,"multipleSelect":false,"randomize":true},"static":false,"type":"radio","version":{"major":1,"minor":0}}}}},"item_shape_type":"item","key":"a63ee349f90da0b1649a0e5dafc99724a34e8a08","name":"2.5 5, 15º","perseus_api_major_version":3,"requires_screen_or_mouse":true,"sha":"a63ee349f90da0b1649a0e5dafc99724a34e8a08","tags":[]},{"author_key":"None","author_names":["Jeff Dodds"],"content_id":"xc742ec6722d8a5c0","content_kind":"AssessmentItem","content_kind_code":"i","created_by":"Key('UserData', 'user_id_key_http://nouserid.khanacademy.org/9af3e69189683d7009d70f10da14a472')","creation_date":"2021-03-31 21:39:01.704072","do_not_publish":false,"hide":false,"id":"xc742ec6722d8a5c0","imported_from_sha":"","item_data":{"answerArea":{"calculator":true,"chi2Table":false,"periodicTable":false,"tTable":false,"zTable":false},"hints":[{"content":"crwdns6970108:0$w$crwdnd6970108:0$wcrwdnd6970108:0{a}crwdnd6970108:0{b}crwdnd6970108:0$wcrwdnd6970108:0{r}crwdnd6970108:0$z$crwdnd6970108:0$z$crwdne6970108:0","images":{},"replace":false,"widgets":{"image 1":{"alignment":"block","graded":true,"options":{"alt":"","backgroundImage":{"height":325,"url":"crwdns6969930:0crwdne6969930:0","width":325},"box":[325,325],"caption":"","labels":[],"range":[[0,10],[0,10]],"static":false,"title":""},"static":false,"type":"image","version":{"major":0,"minor":0}}}},{"content":"crwdns6970458:0{align}crwdnd6970458:0{align}crwdne6970458:0","images":{},"replace":false,"widgets":{}},{"content":"crwdns6970066:0$z$crwdne6970066:0","images":{},"replace":false,"widgets":{}}],"itemDataVersion":{"major":0,"minor":1},"question":{"content":"crwdns6970222:0$zcrwdnd6970222:0$z$crwdne6970222:0","images":{},"widgets":{"radio 1":{"alignment":"default","graded":true,"options":{"choices":[{"content":"crwdns6969988:0crwdne6969988:0","correct":true},{"content":"crwdns6970350:0crwdne6970350:0","correct":false},{"content":"crwdns6969970:0crwdne6969970:0","correct":false,"isNoneOfTheAbove":false},{"content":"crwdns6970556:0crwdne6970556:0","correct":false,"isNoneOfTheAbove":false}],"countChoices":false,"deselectEnabled":false,"displayCount":null,"hasNoneOfTheAbove":false,"multipleSelect":false,"randomize":true},"static":false,"type":"radio","version":{"major":1,"minor":0}}}}},"item_shape_type":"item","key":"f6ac400e8ae9167270f73e9b161b4efaacc2d868","name":"2.6 6, 165º","perseus_api_major_version":3,"requires_screen_or_mouse":true,"sha":"f6ac400e8ae9167270f73e9b161b4efaacc2d868","tags":[]}]